[{
    "name": "שיר פתיחה",
    "audio": "",
    "lyrics":""
},{
    "name": "יהיה מעניין",
    "audio": "",
    "lyrics":""
},{
    "name": "שיר האגדה",
    "audio": "",
    "lyrics":""
},{
    "name": "אחלה חטופה",
    "audio": "",
    "lyrics":""
},{
    "name": "ילדה קסומה",
    "audio": "",
    "lyrics":""
},{
    "name": "הזימון של אסטרות'",
    "audio": "",
    "lyrics":""
},{
    "name": "מארש השיניגאמים",
    "audio": "",
    "lyrics":""
},{
    "name": "הזעם של אסטרות,",
    "audio": "",
    "lyrics":""
},{
    "name": "יש מקום אצלנו",
    "audio": "",
    "lyrics":""
},{
    "name": "ביי לסגנית ושלום לדרקון",
    "audio": "",
    "lyrics":""
},{
    "name": "שובו של מקאי",
    "audio": "",
    "lyrics":""
},{
    "name": "כלא כלא",
    "audio": "",
    "lyrics":""
}]